libsonata/_libsonata.cpython-311-darwin.so
libsonata/__init__.py
libsonata-0.1.33.dist-info/RECORD
libsonata-0.1.33.dist-info/WHEEL
libsonata-0.1.33.dist-info/top_level.txt
libsonata-0.1.33.dist-info/METADATA
libsonata-0.1.33.dist-info/licenses/COPYING.LESSER
libsonata-0.1.33.dist-info/licenses/COPYING
libsonata-0.1.33.dist-info/licenses/AUTHORS.txt
