Metadata-Version: 2.4
Name: libsonata
Version: 0.1.33
Summary: SONATA files reader
Home-page: https://github.com/openbraininstitute/libsonata
Author: Blue Brain Project, EPFL
License: LGPL-3.0-or-later
Requires-Python: >=3.9
License-File: COPYING
License-File: COPYING.LESSER
License-File: AUTHORS.txt
Requires-Dist: numpy>=1.17.3
Provides-Extra: docs
Requires-Dist: sphinx-bluebrain-theme; extra == "docs"
Dynamic: author
Dynamic: description
Dynamic: description-content-type
Dynamic: home-page
Dynamic: license
Dynamic: license-file
Dynamic: provides-extra
Dynamic: requires-dist
Dynamic: requires-python
Dynamic: summary
